fetkutils/__init__.py
fetkutils/tischedule.py
fetkutils-3.5.8.dist-info/METADATA
fetkutils-3.5.8.dist-info/WHEEL
fetkutils-3.5.8.dist-info/entry_points.txt
fetkutils-3.5.8.dist-info/top_level.txt
fetkutils-3.5.8.dist-info/RECORD
