Metadata-Version: 2.4
Name: fetkutils
Version: 3.5.8
Summary: Utility library for the FE-ToolKit project
Author-email: "Timothy J. Giese" <TimothyJGiese@gmail.com>
Keywords: free energy
Classifier: Programming Language :: Python :: 3
Classifier: Development Status :: 5 - Production/Stable
Requires-Python: >=3.7
Requires-Dist: numpy
Requires-Dist: scipy
Requires-Dist: matplotlib
Requires-Dist: netCDF4
Requires-Dist: rdkit
Requires-Dist: setuptools
Requires-Dist: importlib
Requires-Dist: importlib-metadata
